welib/__init__.py
welib/BEM/_OTHER.py
welib/BEM/_TODO.py
welib/BEM/__init__.py
welib/BEM/highthrust.py
welib/BEM/idealrotors.py
welib/BEM/steadyBEM.py
welib/BEM/unsteadyBEM.py
welib/BEM/tests/__init__.py
welib/BEM/tests/test_BEM.py
welib/BEM/tests/test_BEM_unsteady.py
welib/BEM/tests/test_run_Examples.py
welib/CFD/__init__.py
welib/CFD/_vorticity-rz - Copy.py
welib/CFD/_vorticity-rz.py
welib/CFD/_vorticity-rz_lesswalls.py
welib/CFD/axisym_streamf.py
welib/CFD/tests/__init__.py
welib/CFD/tests/test_axisym_streamf.py
welib/FEM/__init__.py
welib/FEM/beam2d.py
welib/FEM/cable.py
welib/FEM/direct_elimination.py
welib/FEM/fem_beam.py
welib/FEM/fem_core.py
welib/FEM/fem_elements.py
welib/FEM/fem_model.py
welib/FEM/fem_sympy.py
welib/FEM/frame2d.py
welib/FEM/frame3d.py
welib/FEM/frame3dlin.py
welib/FEM/graph.py
welib/FEM/reduction.py
welib/FEM/timoshenko.py
welib/FEM/utils.py
welib/FEM/tests/_FEMBeam2SID.py
welib/FEM/tests/__init__.py
welib/FEM/tests/test_beam_linear_element.py
welib/FEM/tests/test_frame3d.py
welib/FEM/tests/test_reduction.py
welib/FEM/tests/test_run_Examples.py
welib/airfoils/DynamicStall.py
welib/airfoils/Polar.py
welib/airfoils/__init__.py
welib/airfoils/tests/__init__.py
welib/airfoils/tests/test_dynamic_stall.py
welib/airfoils/tests/test_polar_interp.py
welib/airfoils/tests/test_polar_manip.py
welib/airfoils/tests/test_polar_params.py
welib/airfoils/tests/test_run_Examples.py
welib/beams/__init__.py
welib/beams/theory.py
welib/beams/examples/Ex1_BeamModes.py
welib/beams/examples/__init__.py
welib/beams/tests/__init__.py
welib/beams/tests/test_theory.py
welib/ctrl/_BodePlot.py
welib/ctrl/__init__.py
welib/ctrl/_secord-matlab.py
welib/ctrl/_secord_transfer.py
welib/dyninflow/DynamicInflow.py
welib/dyninflow/__init__.py
welib/dyninflow/examples/Ex1_StepUp.py
welib/dyninflow/examples/__init__.py
welib/fast/FASTLin.py
welib/fast/__init__.py
welib/fast/beamdyn.py
welib/fast/campbell.py
welib/fast/case_gen.py
welib/fast/fastfarm.py
welib/fast/fastlib.py
welib-0.0.1.dist-info/LICENSE.TXT
welib-0.0.1.dist-info/METADATA
welib-0.0.1.dist-info/WHEEL
welib-0.0.1.dist-info/top_level.txt
welib-0.0.1.dist-info/RECORD
