Metadata-Version: 2.1
Name: welib
Version: 0.0.1
Summary: Wind Energy Library
Home-page: http://github.com/ebranlard/welib/
Author: Emmanuel Branlard
Author-email: lastname@gmail.com
License: MIT
Platform: UNKNOWN
Classifier: Development Status :: 5 - Production/Stable
Classifier: Environment :: Console
Classifier: Intended Audience :: Science/Research
Classifier: Intended Audience :: Education
Classifier: Intended Audience :: End Users/Desktop
Classifier: Intended Audience :: Developers
Classifier: License :: OSI Approved :: MIT License
Classifier: Operating System :: MacOS :: MacOS X
Classifier: Operating System :: Microsoft :: Windows
Classifier: Operating System :: POSIX
Classifier: Operating System :: Unix
Classifier: Programming Language :: Python
Classifier: Topic :: Scientific/Engineering
Classifier: Topic :: Scientific/Engineering :: Atmospheric Science
Classifier: Topic :: Scientific/Engineering :: Hydrology
Classifier: Topic :: Scientific/Engineering :: Mathematics
Classifier: Topic :: Scientific/Engineering :: Physics
Requires-Python: >=3.6
License-File: LICENSE.TXT
Requires-Dist: matplotlib
Requires-Dist: numpy
Requires-Dist: scipy
Requires-Dist: future
Requires-Dist: pandas
Requires-Dist: sympy
Requires-Dist: xlrd
Requires-Dist: chardet
Provides-Extra: docs
Requires-Dist: sphinxcontrib-napoleon (>=0.7) ; extra == 'docs'
Requires-Dist: readthedocs-sphinx-ext (>=0.5.15) ; extra == 'docs'
Requires-Dist: Sphinx (>=2.0) ; extra == 'docs'
